pychartjs/Color.py
pychartjs/Opt.py
pychartjs/__init__.py
pychartjs/pychartjs.py
pychartjs/utils.py
pyChart.JS-0.3.0.dist-info/LICENSE
pyChart.JS-0.3.0.dist-info/METADATA
pyChart.JS-0.3.0.dist-info/WHEEL
pyChart.JS-0.3.0.dist-info/top_level.txt
pyChart.JS-0.3.0.dist-info/RECORD
