Metadata-Version: 2.1
Name: pyChart.JS
Version: 0.3.0
Summary: A clean, class-based implementation of Chart.JS for Django, Flask and any other Python project
Home-page: https://github.com/IridiumIO/pyChart.JS
Author: Iridium IO, ImminentFate
Author-email: iridium.io@outlook.com
License: UNKNOWN
Keywords: django python objective class-based chart chartjs chart.js
Platform: UNKNOWN
Classifier: Programming Language :: Python :: 3
Classifier: Programming Language :: Python :: 3.7
Classifier: License :: OSI Approved :: MIT License
Classifier: Operating System :: OS Independent
Classifier: Development Status :: 3 - Alpha
Classifier: Intended Audience :: Developers
Classifier: Natural Language :: English
Classifier: Framework :: Django
Classifier: Topic :: Software Development :: Libraries :: Python Modules
Requires-Python: >=3.6
